uintel/__init__.py
uintel/aws.py
uintel/colours.py
uintel/esri.py
uintel/geometry.py
uintel/install.py
uintel/ogc.py
uintel/query.py
uintel/raster.py
uintel/server.py
uintel/slack.py
uintel/sql.py
uintel/fonts/Myriad Pro (TrueType).ttf
uintel/fonts/Rubik (TrueType).ttf
uintel/fonts/Rubik Italic (TrueType).ttf
uintel/styles/ui.mplstyle
uintel-0.4.6.dist-info/LICENSE
uintel-0.4.6.dist-info/METADATA
uintel-0.4.6.dist-info/WHEEL
uintel-0.4.6.dist-info/top_level.txt
uintel-0.4.6.dist-info/RECORD
