Metadata-Version: 2.1
Name: uintel
Version: 0.4.6
Summary: Urban Intelligence's unified Python data analysis toolkit
Home-page: https://uintel.github.io/pyui/
Author: Sam Archie
Author-email: sam.archie@urbanintelligence.co.nz
License: MIT
Classifier: Development Status :: 4 - Beta
Classifier: Intended Audience :: End Users/Desktop
Classifier: Intended Audience :: Science/Research
Classifier: Operating System :: Microsoft :: Windows
Classifier: Operating System :: POSIX
Classifier: License :: OSI Approved :: MIT License
Classifier: Programming Language :: Python :: 3 :: Only
Classifier: Natural Language :: English
License-File: LICENSE
Requires-Dist: matplotlib
Requires-Dist: colour
Requires-Dist: slack-sdk
Requires-Dist: sqlalchemy
Requires-Dist: sqlalchemy-utils
Requires-Dist: psycopg2
Requires-Dist: pyyaml
Requires-Dist: tqdm
Requires-Dist: paramiko
Requires-Dist: boto3
Requires-Dist: geopandas
Requires-Dist: esridump
Requires-Dist: requests
Requires-Dist: topojson
Requires-Dist: OWSLib
Provides-Extra: full
Requires-Dist: gdal ; extra == 'full'
Requires-Dist: rasterio ; extra == 'full'
